hvdata/__about__.py
hvdata/__init__.py
hvdata-0.0.1a1.dist-info/METADATA
hvdata-0.0.1a1.dist-info/WHEEL
hvdata-0.0.1a1.dist-info/licenses/LICENSE.txt
hvdata-0.0.1a1.dist-info/RECORD
